goog/__init__.py
goog/cdn.py
goog/proxy.py
goog/__metadata__/DISCLAIMER.md
goog/__metadata__/LICENSE
goog/__metadata__/README.md
goog/__metadata__/__init__.py
goog/__metadata__/requirements.txt
goog/colab/__init__.py
goog/colab/utils.py
goog/colab/aria2/__init__.py
goog/colab/aria2/core.py
goog/colab/browser/__init__.py
goog/colab/browser/core.py
goog/colab/browser/webkit_browser.py
goog/colab/browser/webkit_browser_utils.py
goog/colab/cell/__init__.py
goog/colab/cell/core.py
goog/colab/cell/utils.py
goog/colab/client/__init__.py
goog/colab/client/core.py
goog/colab/rclone/__init__.py
goog/colab/rclone/core.py
goog/colab/rclone/utils.py
goog/colab/server/__init__.py
goog/colab/server/core.py
goog/colab/server/webkit_http_rpc.py
goog/colab/server/webkit_rpc.py
goog/colab/server/wrcs.py
goog/drive/__init__.py
goog/drive/core.py
goog/mirror/__init__.py
goog/mirror/all.py
goog/mirror/by_image.py
goog/mirror/images.py
goog/mirror/utils.py
goog-0.6.93.dist-info/METADATA
goog-0.6.93.dist-info/WHEEL
goog-0.6.93.dist-info/top_level.txt
goog-0.6.93.dist-info/RECORD
