Metadata-Version: 2.1
Name: goog
Version: 0.6.93
Summary: Google Search API using public mirrors.<br/>Web resources proxying using Google Translate internals.<br/>Google Colab tools such as tunnel, web scraping, rclone.<br/>Google Drive API for batch downloads.
Home-page: http://code.foxe6.kozow.com/goog/
Author: f̣ộx̣ệ6
Author-email: foxe6@pm.me
License: AGPL-3.0
Project-URL: Sourcecode, http://code.foxe6.kozow.com/goog.zip
Project-URL: Documentation, http://code.foxe6.kozow.com/goog/docs/
Project-URL: Example, http://code.foxe6.kozow.com/goog/test/
Project-URL: Funding, https://paypal.me/foxe6
Project-URL: Say Thanks!, https://saythanks.io/to/foxe6
Keywords: google search drive translate proxy cdn mirror colab tool api tunnel
Platform: UNKNOWN
Classifier: Programming Language :: Python :: 3.9
Classifier: Topic :: Utilities
Classifier: Natural Language :: English
Classifier: Intended Audience :: Developers
Classifier: License :: OSI Approved :: GNU Affero General Public License v3
Classifier: Operating System :: MacOS
Classifier: Operating System :: POSIX
Classifier: Operating System :: Microsoft :: Windows :: Windows 10
Classifier: Development Status :: 5 - Production/Stable
Requires-Python: >=3.5
Requires-Dist: omnitools (>=0.0.1)
Requires-Dist: requests (>=0.0.1)
Requires-Dist: remotescreen (>=0.0.1)
Requires-Dist: nest-asyncio (>=0.0.1)
Requires-Dist: tornado (==5.1.1)
Requires-Dist: playwright (>=0.0.1)
Requires-Dist: unencryptedsocket (>=0.0.1)
Requires-Dist: cloudscraper (>=0.0.1)
Requires-Dist: html2text (>=0.0.1)
Requires-Dist: pydrive2 (>=0.0.1)
Requires-Dist: chardet (>=0.0.1)
Requires-Dist: lxml (>=0.0.1)
